{
  "日程": [380,80],
  "日程-竞技场": [700,230],
  "日程-英雄试炼": [824,242],
  "我愿意接受试炼": [700,450],
  "战斗状态": [960,715,1020,775],
  "自动按钮": [990,745],
  "日程-竞技场-挑战1": [890,210],
  "日程-竞技场-挑战2": [890,300],
  "日程-竞技场-挑战3": [890,390],
  "日程-竞技场-挑战4": [890,490],
  "日程-竞技场-挑战5": [890,585],
  "交易-烹饪": [174,340,366,374],
  "交易-装备": [177,298,361,328],
  "草药丹药": [177,386,367,417],
  "高品丹药": [178,431,366,461],
  "古董": [179,476,366,506],
  "逛摊-购买": [648,666],
  "逛摊-n1": [547,229],
  "逛摊-n2": [794,232],
  "逛摊-n3": [541,331],
  "逛摊-n4": [796,325],
  "逛摊-n5": [526,411],
  "逛摊-n6": [785,410],
  "逛摊-n7": [545,494],
  "逛摊-n8": [789,497],
  "逛摊-n9": [537,582],
  "逛摊-n10": [787,587],
  "竞技场-挑战1": [890,210],
  "竞技场-挑战2": [890,300],
  "竞技场-挑战3": [890,390],
  "竞技场-挑战4": [890,490],
  "竞技场-挑战5": [890,585],
  "科举-问题区": [303,263,737,410],
  "任务栏展开": [991,150,1022,183],
  "试练-周一": [95,70],
  "试练-周二": [162,70],
  "试练-周三": [239,70],
  "试练-周四": [309,70],
  "试练-周五": [390,70],
  "试练-周六": [460,70],
  "试练-周日": [527,70],
  "试练-周一-1":[219,564],
  "试练-周一-2":[388,624],
  "试练-周一-3":[388,453],
  "试练-周一-4":[621,590],
  "试练-周一-5":[759,448]
}